qqocr/__init__.py
qqocr/main.py
qqocr-0.3.2.dist-info/LICENSE
qqocr-0.3.2.dist-info/METADATA
qqocr-0.3.2.dist-info/WHEEL
qqocr-0.3.2.dist-info/top_level.txt
qqocr-0.3.2.dist-info/RECORD
