Metadata-Version: 2.1
Name: qqocr
Version: 0.3.2
Summary: A package used for OCR.
Author-email: zx <jugking6688@gmail.com>
Classifier: Programming Language :: Python :: 3
Classifier: License :: OSI Approved :: MIT License
Classifier: Operating System :: OS Independent
Requires-Python: >=3.8
License-File: LICENSE
Requires-Dist: opencv-python
Requires-Dist: dill
